{
  "date": "2026-01-23",
  "hebrewDate": "ืืณ ืฉืื ืืณืชืฉืคืดื (5 ะจะฒะฐัะฐ 5786)",
  "parsha": "ะะพ",
  "dayType": "ะััะฝะธัะฐ - ะญัะตะฒ ะจะฐะฑะฑะพั ะะพะดะตั",
  "dedication": "ะะพะดะณะพัะพะฒะบะฐ ะบ ะัะด ะจะฒะฐั - 16-ะน ืกึฐืขึดืืฃ ะะพัะธ ะะตะณะฐะฝะธ",
  "specialDay": "ืขึถืจึถื ืฉึทืืึธึผืช ืงึนืึถืฉื - ะะฐะฝัะฝ ัะฒััะพะน ะกัะฑะฑะพัั, ะฟัะธะฑะปะธะถะตะฝะธะต ะบ ะัะด ะจะฒะฐั",
  "sections": [
    {
      "id": "chumash",
      "title": "ะฅะฃะะะจ",
      "subtitle": "ะะพ - ะะตะฝั 6 (ะจะธัะธ)",
      "icon": "๐",
      "category": "chumash",
      "color": "#FF6B6B",
      "points": 50,
      "content": {
        "title": "ืึทืึทึผืช ืึฐึผืืึนืจืึนืช - ะััะพะด ะธะท ะะณะธะฟัะฐ!",
        "paragraphs": [
          {
            "type": "text",
            "text": "ะะพะฒะฝะพ ะฒ ะฟะพะปะฝะพัั ะัะตะฒััะฝะธะน ัะพะฒะตััะฐะตั ะะฐะบะฐัะฐ ะะตัะพัะพั, ะธ ะตะณะธะฟััะฝะต ะฒ ัะฟะตัะบะต ะฒัะณะพะฝััั ะตะฒัะตะตะฒ ะธะท ะะณะธะฟัะฐ!"
          },
          {
            "type": "heading",
            "text": "ืึฒืฆืึนืช ืึทืึทึผืึฐืึธื - ะะพะฒะฝะพ ะฒ ะฟะพะปะฝะพัั"
          },
          {
            "type": "highlight",
            "text": "ะะพะฒะฝะพ ะฒ ะฟะพะปะฝะพัั ะัะตะฒััะฝะธะน ัะฑะธะป ะฒัะตั ะฟะตัะฒะตะฝัะตะฒ ะฒ ะะณะธะฟัะต - ะฟะตัะฒะตะฝัะตะฒ ะปัะดะตะน (ะฒะบะปััะฐั ะฝะตะตะฒัะตะนัะบะธั ัะฐะฑะพะฒ) ะธ ะฟะตัะฒะตะฝัะตะฒ ะถะธะฒะพัะฝัั."
          },
          {
            "type": "text",
            "text": "ะะดะธะฝััะฒะตะฝะฝัะน ะฟะตัะฒะตะฝะตั, ะบะพัะพััะน ะฝะต ัะผะตั, ะฑัะป ะคะฐัะฐะพะฝ."
          },
          {
            "type": "teaching",
            "title": "ะะพัะตะผั ะคะฐัะฐะพะฝ ะพััะฐะปัั ะถะธะฒ?",
            "text": "ะัะตะฒััะฝะธะน ัะพัะตะป, ััะพะฑั ะพะฝ ัะฒะธะดะตะป ััะดะตัะฐ ืงึฐืจึดืืขึทืช ืึทื ืกืึผืฃ (ะะฐััะตัะตะฝะธั ะะพัั), ััะพะฑั ะพะฝ ะทะฝะฐะป ะธ ัะฐััะบะฐะทะฐะป ะดััะณะธะผ, ััะพ ะัะตะฒััะฝะธะน - ะฅะพะทัะธะฝ ะผะธัะฐ!"
          },
          {
            "type": "heading",
            "text": "ะัะพะฑัะถะดะตะฝะธะต ะฒ ัะถะฐัะต"
          },
          {
            "type": "text",
            "text": "ะคะฐัะฐะพะฝ ะฟัะพัะฝัะปัั, ะฐ ะทะฐัะตะผ ะฟะพััะป ะธ ัะฐะทะฑัะดะธะป ะฒัะตั ัะฒะพะธั ัะปัะณ."
          },
          {
            "type": "text",
            "text": "ะัะต ะตะณะธะฟััะฝะต ะฟัะพัะฝัะปะธัั ัะพะถะต."
          },
          {
            "type": "text",
            "text": "ะัะต ัะฒะธะดะตะปะธ, ััะพ ะฟะตัะฒะตะฝัั ัะผะตัะปะธ!"
          },
          {
            "type": "highlight",
            "text": "ะ ะบะฐะถะดะพะผ ะดะพะผะต ะฑัะป ัะพัั ะฑั ะพะดะธะฝ ะผัััะฒัะน ัะตะปะพะฒะตะบ. ะะตัั ะะณะธะฟะตั ะฑัะป ะฟะพะปะพะฝ ะฟะปะฐัะฐ!"
          },
          {
            "type": "heading",
            "text": "ะคะฐัะฐะพะฝ ะฑะตะถะธั ะบ ะะพัะต"
          },
          {
            "type": "text",
            "text": "ะคะฐัะฐะพะฝ ะฒัะฑะตะถะฐะป ะธะท ะดะฒะพััะฐ ะฟะพััะตะดะธ ะฝะพัะธ, ััะพะฑั ะฝะตะผะตะดะปะตะฝะฝะพ ะฝะฐะนัะธ ะะพัะต ะธ ะะฐัะพะฝะฐ!"
          },
          {
            "type": "text",
            "text": "ะะฝ ัะบะฐะทะฐะป ะธะผ, ััะพ ะฒัะต ะตะฒัะตะธ ะดะพะปะถะฝั ะฟะพะบะธะฝััั ะะณะธะฟะตั - ัะพ ะฒะทัะพัะปัะผะธ, ะดะตััะผะธ ะธ ะฒัะตะผะธ ะธั ะถะธะฒะพัะฝัะผะธ!"
          },
          {
            "type": "text",
            "text": "ะะตะบะพัะพััะต ะตะฒัะตะธ ะฑะพัะปะธัั ะฒััะพะดะธัั ะฒ ะฟััััะฝั, ะฝะพ ะตะณะธะฟััะฝะต ะณะพะฒะพัะธะปะธ ะธะผ ัะพัะพะฟะธัััั ะธ ะธะดัะธ!"
          },
          {
            "type": "heading",
            "text": "ะงัะพ ะตะฒัะตะธ ะฒะทัะปะธ ั ัะพะฑะพะน"
          },
          {
            "type": "text",
            "text": "ะฃ ะตะฒัะตะตะฒ ะฝะต ะฑัะปะพ ะฒัะตะผะตะฝะธ ะธัะฟะตัั ัะปะตะฑ ัััะพะผ, ะฟะพััะพะผั ะพะฝะธ ะฟัะพััะพ ะฒะทัะปะธ ัััะพะต ัะตััะพ, ะบะพัะพัะพะต ัะดะตะปะฐะปะธ, ะธ ะพััะฐัะบะธ ืึทืฆึธึผื ะธ ืึธืจืึนืจ ะพั ะะพัะฑะฐะฝ ะะตัะฐั ะฟัะพัะปะพะน ะฝะพัะธ."
          },
          {
            "type": "example",
            "title": "ะะพัะตะผั ะฝะฐ ัะฟะธะฝะฐั?",
            "text": "ะะฝะธ ะฝะตัะปะธ ััะพ ะฝะฐ ัะฟะธะฝะฐั, ะฟะพัะพะผั ััะพ ัะพัะตะปะธ ะฝะตััะธ ะผะธัะฒั! ะะฝะธ ะฟะพะฟัะพัะธะปะธ ั ะตะณะธะฟััะฝ ะทะพะปะพัะพ, ัะตัะตะฑัะพ ะธ ะพะดะตะถะดั ะดะปั ะดะพัะพะณะธ ะธ ะฟะพะปะพะถะธะปะธ ะธั ะฝะฐ ะพัะปะพะฒ."
          },
          {
            "type": "text",
            "text": "ะะตะฝัะธะฝั ัะฐะบะถะต ะฒะทัะปะธ ืชึปึผืคึดึผืื (ัะธะผะฑััะธะฝั), ะฟะพัะพะผั ััะพ ะฑัะปะธ ัะฒะตัะตะฝั, ััะพ ะัะตะฒััะฝะธะน ัะดะตะปะฐะตั ััะดะตัะฐ, ะธ ัะพัะตะปะธ ะฑััั ะณะพัะพะฒัะผะธ ะฟะตัั ะธ ัะฐะฝัะตะฒะฐัั!"
          },
          {
            "type": "heading",
            "text": "ืึฒืจืึนื ืืึนืกึตืฃ - ะัะพะฑ ะะพัะตัะฐ"
          },
          {
            "type": "text",
            "text": "ะะพัะต ะฟะพะทะฐะฑะพัะธะปัั ะพ ัะพะผ, ััะพะฑั ะฒัะฝััั ืัะพะฑ ะะพัะตัะฐ ะธะท ะะธะปะฐ, ะบะฐะบ ะฑัะปะพ ะพะฑะตัะฐะฝะพ ะะพัะตัั."
          },
          {
            "type": "text",
            "text": "ะะฝ ัะฐะบะถะต ะฟัะธะฝัั ะณัะพะฑั ะดััะณะธั ืฉึฐืืึธืึดืื (ะบะพะปะตะฝ)."
          },
          {
            "type": "text",
            "text": "ะะฒัะตะธ ัะฐะบะถะต ะฟัะธะฝะตัะปะธ ะดะตัะตะฒัั, ะบะพัะพััะต ะฟะพัะฐะดะธะป ะฏะฐะบะพะฒ, ััะพะฑั ะธัะฟะพะปัะทะพะฒะฐัั ะธั ะฟะพะทะถะต ะดะปั ืึดืฉึฐืืึธึผื (ะะตัะตะฝะพัะฝะพะณะพ ะฅัะฐะผะฐ)."
          },
          {
            "type": "heading",
            "text": "ืกึปืึนึผืช - ะะตัะฒะฐั ะพััะฐะฝะพะฒะบะฐ"
          },
          {
            "type": "text",
            "text": "ะัะตะฒััะฝะธะน ะฟะพัะปะฐะป ืึทืึฐืึธืึฐ (ะฐะฝะณะตะปะฐ), ััะพะฑั ะฟะพะบะฐะทะฐัั ะตะฒัะตัะผ, ะบัะดะฐ ะธะดัะธ."
          },
          {
            "type": "text",
            "text": "ะัะต ะฟะพัะปะธ ะธะท ะะฐะฐะผัะตัะฐ (ะพะบะพะปะพ ะะพัะตะฝะฐ) ะฒ ะผะตััะพ, ะบะพัะพัะพะต ะฝะฐะทะพะฒัั \"ะกัะบะพั\", ะพะบะพะปะพ ืึทื ืกืึผืฃ (ะขัะพััะฝะธะบะพะฒะพะณะพ ะะพัั)."
          },
          {
            "type": "highlight",
            "text": "ะะพัะต ะฟะพััะธัะฐะป ะตะฒัะตะตะฒ, ะธ ะฑัะปะพ ะพะบะพะปะพ 600,000 ะผัะถัะธะฝ ััะฐััะต 20 ะปะตั!"
          },
          {
            "type": "text",
            "text": "ะััะฟะฟะฐ ะณะพะตะฒ, ะฝะฐะทัะฒะฐะตะผะฐั ืขึตืจึถื ืจึทื, ะบะพัะพััะต ัะพัะตะปะธ ะฟัะธัะพะตะดะธะฝะธัััั ะบ ะตะฒัะตัะผ, ัะพะถะต ะฟัะธัะปะฐ."
          },
          {
            "type": "text",
            "text": "ะ ะกัะบะพั ะตะฒัะตะธ ะธัะฟะตะบะปะธ ัะตััะพ ะฒ ะผะฐัั."
          },
          {
            "type": "text",
            "text": "ะญัะฐ ะผะฐัะฐ ัะฒะฐัะธะปะฐ ะตะฒัะตัะผ ะฝะฐ ะผะตััั, ะฟะพะบะฐ ะฝะต ะฝะฐัะฐะป ะฟะฐะดะฐัั ืึธื (ะผะฐะฝะฝะฐ ั ะฝะตะฑะตั)!"
          },
          {
            "type": "heading",
            "text": "210 ะปะตั ะฒ ืึธึผืืึผืช"
          },
          {
            "type": "text",
            "text": "ะขะพัะฐ ัะฐััะบะฐะทัะฒะฐะตั ะฝะฐะผ, ััะพ ะตะฒัะตะธ ะฑัะปะธ ะฒ ะะพะปัั ะฒ ะะณะธะฟัะต 210 ะปะตั."
          },
          {
            "type": "text",
            "text": "430 ะปะตั ะฟัะพัะปะพ ั ืึฐึผืจึดืืช ืึตึผืื ืึทืึฐึผืชึธืจึดืื (ะกะพัะทะฐ ะผะตะถะดั ะงะฐัััะผะธ), ะบะพะณะดะฐ ะัะตะฒััะฝะธะน ัะบะฐะทะฐะป ะะฒัะฐะฐะผั, ััะพ ะตะณะพ ะดะตัะธ ะฟะพะนะดัั ะฒ ะะพะปัั."
          },
          {
            "type": "highlight",
            "text": "ะะพะฒะฝะพ ะฒ ะบะพะฝัะต ััะพะณะพ ะฒัะตะผะตะฝะธ ะัะตะฒััะฝะธะน ะฒัะฒะตะป ะตะฒัะตะตะฒ! ะะฝะธ ะฝะต ะพััะฐะปะธัั ะฒ ะะพะปัั ะฝะธ ะฝะฐ ะพะดะฝั ะผะธะฝััั ะดะพะปััะต, ัะตะผ ะฝัะถะฝะพ ะฑัะปะพ."
          },
          {
            "type": "heading",
            "text": "ืึตืื ืฉึดืืึปึผืจึดืื - ะะพัั ะะฐัะธัั"
          },
          {
            "type": "text",
            "text": "ะะฐะฒัะตะณะดะฐ ััะฐ ะฝะพัั ะััะพะดะฐ ะธะท ะะณะธะฟัะฐ ะฝะฐะทัะฒะฐะตััั \"ะะตะนะป ะจะธะผััะธะผ\" - ะฝะพัั, ะบะพะณะดะฐ ะัะตะฒััะฝะธะน ะทะฐัะธัะฐะตั ะฝะฐั."
          },
          {
            "type": "heading",
            "text": "ะะพะฟะพะปะฝะธัะตะปัะฝัะต ะทะฐะบะพะฝั ะพ ะะพัะฑะฐะฝ ะะตัะฐั"
          },
          {
            "type": "text",
            "text": "ะ ะบะพะฝัะต ัะตะณะพะดะฝััะฝะตะณะพ ะฅัะผะฐัะฐ ะตััั ะตัั ะฝะตัะบะพะปัะบะพ ะผะธัะฒะพั ะพ ะะพัะฑะฐะฝ ะะตัะฐั:"
          },
          {
            "type": "text",
            "text": "โข ะขะพะปัะบะพ ะตะฒัะตะธ, ะบะพัะพััะต ะฒะตััั ะฒะพ ะัะตะฒััะฝะตะณะพ, ะผะพะณัั ะตััั ะะพัะฑะฐะฝ ะะตัะฐั\nโข ะะปะธ ัะฐะฑ, ะฟัะธะฝะฐะดะปะตะถะฐัะธะน ะตะฒัะตั\nโข ะะพ ะฒัะตะผ ะฝัะถะฝะพ ะธะผะตัั ืึฐึผืจึดืืช (ะพะฑัะตะทะฐะฝะธะต)\nโข ะะฐะฟัะตัะตะฝะพ ะปะพะผะฐัั ะปัะฑัะต ะบะพััะธ ะบะพัะฑะฐะฝะฐ"
          },
          {
            "type": "highlight",
            "text": "ะัะต ะตะฒัะตะธ ัะดะตะปะฐะปะธ ัะพัะฝะพ ัะพ, ััะพ ะัะตะฒััะฝะธะน ะฟัะพัะธะป!"
          }
        ]
      }
    },
    {
      "id": "tehillim",
      "title": "ะขะะะะะ",
      "subtitle": "ะะปะฐะฒั 29-34",
      "icon": "๐ฟ",
      "category": "tehillim",
      "color": "#4ECDC4",
      "points": 40,
      "content": {
        "title": "ะะฐะบ ะฟัะฐะฒะธะปัะฝะพ ะธัะฟะพะปัะทะพะฒะฐัั ะผะฐัะตัะธะฐะปัะฝะพะต",
        "paragraphs": [
          {
            "type": "text",
            "text": "ะกะตะณะพะดะฝััะฝะธะน ะขะตะธะปะธะผ - ะณะปะฐะฒั 29 ัะตัะตะท 34."
          },
          {
            "type": "heading",
            "text": "ะกัะธั ะพ ะดะพะฑัะต ะธ ะผะธัะต"
          },
          {
            "type": "text",
            "text": "ะ ะฟะพัะปะตะดะฝะตะน ะณะปะฐะฒะต ัะตะณะพะดะฝััะฝะตะณะพ ะขะตะธะปะธะผ ะะฐะฒะธะด ะฐะะตะปะตั ะณะพะฒะพัะธั ะฝะฐะผ:"
          },
          {
            "type": "highlight",
            "text": "\"ืกืึผืจ ืึตืจึธืข ืึทืขึฒืฉึตืื ืืึนื ืึทึผืงึตึผืฉื ืฉึธืืืึนื ืึฐืจืืึฐืคึตืืึผ\" - \"ะัะฒะตัะฝะธัั ะพั ะทะปะฐ, ะดะตะปะฐะน ะดะพะฑัะพ, ะธัะธ ะผะธั ะธ ะณะพะฝะธัั ะทะฐ ะฝะธะผ\"."
          },
          {
            "type": "heading",
            "text": "ะะฑัััะฝะตะฝะธะต ะะฐะฐะป ะจะตะผ ะขะพะฒะฐ"
          },
          {
            "type": "text",
            "text": "ะะฐะฐะป ะจะตะผ ะขะพะฒ ะพะฑัััะฝัะตั, ััะพ ะฒ ะบะฐะถะดะพะน ะผะฐัะตัะธะฐะปัะฝะพะน ะฒะตัะธ ะฒ ััะพะผ ะผะธัะต ะตััั ัะฐััั, ะบะพัะพัะฐั ัะพัะพัะฐั, ะธ ัะฐััั, ะบะพัะพัะฐั ะฟะปะพัะฐั."
          },
          {
            "type": "text",
            "text": "ะะฐัะตัะธะฐะปัะฝะพะต ัะฐะผะพ ะฟะพ ัะตะฑะต (ะฑะตะท ะธัะฟะพะปัะทะพะฒะฐะฝะธั ะดะปั ัะฒััะพะน ัะตะปะธ) - ััะพ ะฟะปะพัะพ."
          },
          {
            "type": "text",
            "text": "ะฅะพัะพัะตะต - ััะพ ืึทืึผืึผืช (ะถะธะทะฝะตะฝะฝะพััั) ะัะตะฒััะฝะตะณะพ, ะบะพัะพัะฐั ะดะฐัั ะถะธะทะฝั ััะพะน ะผะฐัะตัะธะฐะปัะฝะพะน ะฒะตัะธ."
          },
          {
            "type": "heading",
            "text": "ืกืึผืจ ืึตืจึธืข - ะัะฒะตัะฝะธัั ะพั ะทะปะฐ"
          },
          {
            "type": "text",
            "text": "ะกัะธั ัะฐััะบะฐะทัะฒะฐะตั ะฝะฐะผ ะพ ัะพะผ, ะบะฐะบ ะผั ะดะพะปะถะฝั ัะผะพััะตัั ะฝะฐ ะผะฐัะตัะธะฐะปัะฝะพะต."
          },
          {
            "type": "text",
            "text": "ะงะตะปะพะฒะตะบ, ะบะพัะพััะน ะธัะฟะพะปัะทัะตั ะผะฐัะตัะธะฐะปัะฝะพะต, ะดะพะปะถะตะฝ ะฑััั \"ะกัั ะะตัะฐ\" - ัะตะผ, ะบัะพ ะพัะฒะพัะฐัะธะฒะฐะตััั ะพั ะฟะปะพัะพะณะพ."
          },
          {
            "type": "highlight",
            "text": "ะั ะฝะต ะดะพะปะถะฝั ัะพัะตัั ัะดะพะฒะพะปัััะฒะธะต, ะบะพัะพัะพะต ะฟะพะปััะฐะตะผ ะพั ะผะฐัะตัะธะฐะปัะฝะพะณะพ."
          },
          {
            "type": "heading",
            "text": "ืขึฒืฉึตืื ืืึนื - ะะตะปะฐะน ะดะพะฑัะพ"
          },
          {
            "type": "text",
            "text": "ะะผะตััะพ ััะพะณะพ ะผั ะดะพะปะถะฝั ะฑััั \"ะัะต ะขะพะฒ\" - ะฒัะฑะธัะฐัั ัะพัะตัั ะฟะพะปััะธัั ะฟะพะผะพัั ะพั ะถะธะทะฝะตะฝะฝะพััะธ ะัะตะฒััะฝะตะณะพ, ะบะพัะพัะฐั ะฒะฝัััะธ."
          },
          {
            "type": "heading",
            "text": "ืึทึผืงึตึผืฉื ืฉึธืืืึนื - ะัะธ ะผะธั"
          },
          {
            "type": "text",
            "text": "ะะฐัะตะผ, ะบะพะณะดะฐ ะผั ะฝะต ะธัะฟะพะปัะทัะตะผ ะผะฐัะตัะธะฐะปัะฝะพะต ะดะปั ัะณะพะธััะธัะฝัั ะฟัะธัะธะฝ, ะผั ะดะพะปะถะฝั ะฟะพะฟััะฐัััั ัะดะตะปะฐัั ืฉึธืืืึนื ะผะตะถะดั ะถะธะทะฝะตะฝะฝะพัััั ะัะตะฒััะฝะตะณะพ ะธ ะผะฐัะตัะธะฐะปัะฝะพะน ะฒะตััั."
          },
          {
            "type": "text",
            "text": "ะะฐะบ ะผั ััะพ ะดะตะปะฐะตะผ?"
          },
          {
            "type": "highlight",
            "text": "ะัะฟะพะปัะทัั ะผะฐัะตัะธะฐะปัะฝะพะต ะดะปั ัะตะปะตะน, ะดะปั ะบะพัะพััั ะัะตะฒััะฝะธะน ัะพัะตั, ััะพะฑั ะพะฝะพ ะธัะฟะพะปัะทะพะฒะฐะปะพัั - ะดะปั ะฒัะฟะพะปะฝะตะฝะธั ะผะธัะฒะพั ะธ ะดะปั ัะพะณะพ, ััะพะฑั ะธะผะตัั ัะธะปั ัะปัะถะธัั ะัะตะฒััะฝะตะผั!"
          },
          {
            "type": "heading",
            "text": "ะขัะธ ัะฐะณะฐ ะธัะฟะพะปัะทะพะฒะฐะฝะธั ะผะฐัะตัะธะฐะปัะฝะพะณะพ"
          },
          {
            "type": "example",
            "title": "ะัะฐะฒะธะปัะฝัะน ะฟะพะดัะพะด",
            "text": "1. **ะกัั ะะตัะฐ** - ะะต ัะพัะตัั ัะดะพะฒะพะปัััะฒะธะต ะพั ัะฐะผะพะณะพ ะผะฐัะตัะธะฐะปัะฝะพะณะพ\n2. **ะัะต ะขะพะฒ** - ะฅะพัะตัั ะฟะพะผะพัั ะพั ะฑะพะถะตััะฒะตะฝะฝะพะน ะถะธะทะฝะตะฝะฝะพััะธ ะฒะฝัััะธ\n3. **ะะฐะบะตั ะจะฐะปะพะผ** - ะัะฟะพะปัะทะพะฒะฐัั ะดะปั ะผะธัะฒะพั ะธ ัะปัะถะตะฝะธั ะัะตะฒััะฝะตะผั"
          },
          {
            "type": "text",
            "text": "ะะพะณะดะฐ ะผั ะธัะฟะพะปัะทัะตะผ ะผะฐัะตัะธะฐะปัะฝะพะต ะฟัะฐะฒะธะปัะฝะพ, ะผั ะดะตะปะฐะตะผ ัะฐะปะพะผ ะผะตะถะดั ัะธะทะธัะตัะบะธะผ ะผะธัะพะผ ะธ ะดััะพะฒะฝัะผ ัะฒะตัะพะผ ะัะตะฒััะฝะตะณะพ!"
          }
        ]
      }
    },
    {
      "id": "tanya",
      "title": "ะขะะะะฏ",
      "subtitle": "ะะธะบััะตะน ะะผะฐัะธะผ - ะะปะฐะฒะฐ 20",
      "icon": "๐",
      "category": "tanya",
      "color": "#45B7D1",
      "points": 45,
      "content": {
        "title": "ะะฐะถะดะฐั ืึดืฆึฐืึธื ัะพะตะดะธะฝัะตั ั ะัะตะฒััะฝะธะผ",
        "paragraphs": [
          {
            "type": "text",
            "text": "ะะปััะตั ะะตะฑะต ััะธั ะฝะฐั, ััะพ ะผั ะผะพะถะตะผ ะธัะฟะพะปัะทะพะฒะฐัั ะพัะพะฑัั ัะธะปั, ะฒัััะพะตะฝะฝัั ะฒ ะดััั ะบะฐะถะดะพะณะพ ะตะฒัะตั, ััะพะฑั ะฟะพะฑะตะถะดะฐัั ืึถืคึถืฉื ืึทืึทึผืึฒืึดืืช (ะะธะฒะพัะฝัั ะััั) ะฒัั ะฒัะตะผั!"
          },
          {
            "type": "heading",
            "text": "ะะฐะบ ัะฐะฑะพัะฐะตั ืจืึผืึท ืฉึฐืืืึผืช"
          },
          {
            "type": "text",
            "text": "ะะตัะตั ะฐะะตะฐะผะธั ะผะพะถะตั ะทะฐััะฐะฒะธัั ะฝะฐั ัะดะตะปะฐัั ะณัะตั ัะพะปัะบะพ ะดะฐะฒะฐั ะฝะฐะผ ะัะฐั ะจััั - ะณะปัะฟัั ะผััะปั."
          },
          {
            "type": "text",
            "text": "ะะฝะฐ ะพะฑะผะฐะฝัะฒะฐะตั ะฝะฐั, ัะฑะตะถะดะฐั, ััะพ ะฝะฐั ะณัะตั ะฝะต ะฒะฐะถะตะฝ."
          },
          {
            "type": "text",
            "text": "ะะพ ะะตัะตั ะฐะะตะฐะผะธั ะผะพะถะตั ัะฑะตะดะธัั ะฝะฐั ััะพะน ะณะปัะฟะพะน ะผััะปัั ัะพะปัะบะพ ะฑะพะปัััั ัะฐััั ะฒัะตะผะตะฝะธ."
          },
          {
            "type": "heading",
            "text": "ะงัะพ ะพะฝะฐ ะะะะะะะ ะฝะต ะผะพะถะตั ัะฑะตะดะธัั"
          },
          {
            "type": "highlight",
            "text": "ะะดะฝะฐ ะฒะตัั, ะฒ ะบะพัะพัะพะน ะพะฝะฐ ะะะะะะะ ะฝะต ะผะพะถะตั ัะฑะตะดะธัั ะฝะฐั: ััะพ ะพัะดะตะปะตะฝะธะต ะพั ะัะตะฒััะฝะตะณะพ ะฝะต ะฒะฐะถะฝะพ!"
          },
          {
            "type": "text",
            "text": "ะะฐะถะดัะน ะตะฒัะตะน ะฟะพะฝะธะผะฐะตั, ััะพ ะฟะพัะตัั ัะฒัะทะธ ั ะัะตะฒััะฝะธะผ ะธ ั ะตะฒัะตะนััะฒะพะผ - ะพัะตะฝั ะฒะฐะถะฝะพะต ะดะตะปะพ."
          },
          {
            "type": "text",
            "text": "ะะฐะถะดัะน ะตะฒัะตะน ะณะพัะพะฒ ะดะฐะถะต ะพัะดะฐัั ะถะธะทะฝั, ััะพะฑั ะฝะต ะฑััั ะพัะดะตะปัะฝะฝัะผ ะพั ะัะตะฒััะฝะตะณะพ, ะฝะต ะดะฐะน ะ-ะณ, ะธ ะพััะฐะฒะฐัััั ะตะฒัะตะตะผ!"
          },
          {
            "type": "heading",
            "text": "ืึทืึฒืึธื ืึฐืกึปืชึถึผืจึถืช - ะกะตะบัะตัะฝะฐั ัะธะปะฐ"
          },
          {
            "type": "text",
            "text": "ะญัะพ ัะธะปะฐ ะะฐะฒะฐ ะะตัััะตัะตั - ะพัะตะฝั ะผะพัะฝะฐั ะปัะฑะพะฒั ะบ ะัะตะฒััะฝะตะผั, ะบะพัะพัะฐั ัะฒะปัะตััั ัะฐัััั ะดััะธ ะบะฐะถะดะพะณะพ ะตะฒัะตั."
          },
          {
            "type": "highlight",
            "text": "ะะพััะพะผั, ะตัะปะธ ะผั ะฟัะพััะพ ะพัะพะทะฝะฐะตะผ, ััะพ ะะะะกะขะะะขะะะฌะะ ะะะะะซะ ะณัะตั ะพัะดะตะปัะตั ะฝะฐั ะพั ะัะตะฒััะฝะตะณะพ, ัะพะณะดะฐ ะฝะธะบะฐะบะพะน ะัะฐั ะจััั ะฝะธะบะพะณะดะฐ ะฝะต ัะผะพะถะตั ัะฑะตะดะธัั ะฝะฐั, ััะพ ััะพ ะฝะต ะฒะฐะถะฝะพ!"
          },
          {
            "type": "heading",
            "text": "ืขึฒืฉึถืืจึถืช ืึทืึดึผืึฐึผืจืึนืช - ะััะพัะฝะธะบ ะฒัะตั ะผะธัะฒะพั"
          },
          {
            "type": "text",
            "text": "ะะปััะตั ะะตะฑะต ะฟะพะบะฐะทัะฒะฐะตั ะฝะฐะผ, ะณะดะต ะผั ะฒะธะดะธะผ, ััะพ ะดะตะนััะฒะธัะตะปัะฝะพ ะบะฐะถะดะฐั ะผะธัะฒะฐ - ััะพ ะบะฐะบ ะฒะตัะฐ ะฒะพ ะัะตะฒััะฝะตะณะพ, ะฐ ะบะฐะถะดัะน ะณัะตั - ะบะฐะบ ัะปัะถะตะฝะธะต ะธะดะพะปะฐะผ ะธ ะพัะดะตะปะตะฝะธะต ะพั ะัะตะฒััะฝะตะณะพ, ะฝะต ะดะฐะน ะ-ะณ."
          },
          {
            "type": "text",
            "text": "ะััั ะดะฒะต ะณะปะฐะฒะฝัะต ะผะธัะฒะพั ะพ ัะฒัะทะธ ะธ ะฝะธะบะพะณะดะฐ ะฝะต ะพัะดะตะปะตะฝะธะธ ะพั ะัะตะฒััะฝะตะณะพ."
          },
          {
            "type": "text",
            "text": "ะะฝะธ - ะฟะตัะฒัะต ะดะฒะฐ ะธะท ะะตัััะธ ะะฐะฟะพะฒะตะดะตะน:"
          },
          {
            "type": "text",
            "text": "โข \"ืึธืึนืึดื ืืณ ืึฑืึนืึถืืึธ\" - \"ะฏ ะะพัะฟะพะดั, ะ-ะณ ัะฒะพะน\"\nโข \"ืึนื ืึดืึฐืึถื ืึฐืึธ ืึฑืึนืึดืื ืึฒืึตืจึดืื\" - \"ะะฐ ะฝะต ะฑัะดะตั ั ัะตะฑั ะดััะณะธั ะฑะพะณะพะฒ\""
          },
          {
            "type": "heading",
            "text": "ะัะต ะผะธัะฒะพั ะฒะบะปััะตะฝั ะฒ ะดะฒะฐ ัะตัะตะฝะธั"
          },
          {
            "type": "text",
            "text": "ะะตะผะฐัะฐ ััะธั ะฝะฐั, ััะพ ะฒัะต ืึดืฆึฐืึนืช ืขึฒืฉึตืื (ะะพะปะพะถะธัะตะปัะฝัะต ะะฐะฟะพะฒะตะดะธ) ะฟัะธัะพะดัั ะพั ะฟะตัะฒะพะณะพ ัะตัะตะฝะธั."
          },
          {
            "type": "text",
            "text": "ะ ะฒัะต ืึดืฆึฐืึนืช ืึนื ืชึทืขึฒืฉึถืื (ะะฐะฟัะตัะธัะตะปัะฝัะต ะะฐะฟะพะฒะตะดะธ) ะฟัะธัะพะดัั ะพั ะฒัะพัะพะณะพ ัะตัะตะฝะธั."
          },
          {
            "type": "teaching",
            "title": "ะะพัะตะผั ัะพะปัะบะพ ะดะฒะฐ ััะปััะฐะปะธ?",
            "text": "ะะพั ะฟะพัะตะผั ะผั ััะปััะฐะปะธ ัะพะปัะบะพ ะฟะตัะฒัะต ะดะฒะฐ ะธะท ะะตัััะธ ะะฐะฟะพะฒะตะดะตะน ะฝะฐะฟััะผัั ะพั ะัะตะฒััะฝะตะณะพ - ะฟะพัะพะผั ััะพ ะพะฝะธ ะฒะบะปััะฐัั ะะกะ ะผะธัะฒะพั!"
          },
          {
            "type": "text",
            "text": "ะขะฐะบ ััะพ, ััะปััะฐะฒ ัะพะปัะบะพ ััะธ ะดะฒะต ะผะธัะฒะพั ะพั ะัะตะฒััะฝะตะณะพ, ะผั ะฝะฐ ัะฐะผะพะผ ะดะตะปะต ัะปััะธะผ ะฒัั ะขะพัั, ะบะพัะพัะฐั ะฒะบะปััะตะฝะฐ ะฒ ะฝะธั, ะฟััะผะพ ะพั ะัะตะฒััะฝะตะณะพ."
          },
          {
            "type": "heading",
            "text": "ะงัะพ ััะพ ะพะทะฝะฐัะฐะตั ะดะปั ะฝะฐั"
          },
          {
            "type": "highlight",
            "text": "ะั ัะฐะบะถะต ะฒะธะดะธะผ ะธะท ััะพะน ะะตะผะฐัั, ััะพ ะบะฐะถะดะฐั ะผะธัะฒะฐ ัะพะตะดะธะฝัะตั ะฝะฐั ั ะัะตะฒััะฝะธะผ - \"ะะฝะพัะธ ะัะตะผ ะญะปะพะบะตัะฐ\"."
          },
          {
            "type": "highlight",
            "text": "ะ ะบะฐะถะดัะน ะณัะตั ะพัะดะตะปัะตั ะฝะฐั - \"ะะพ ะะธะนะต\"."
          },
          {
            "type": "heading",
            "text": "ืึดึผืึฐืึทืจ ืืณ ืฉึธืืึทืึดื ืึทืขึฒืฉืืึผ - ะกะพะทะดะฐะฝะธะต ะผะธัะฐ ัะตััั"
          },
          {
            "type": "text",
            "text": "ะงัะพะฑั ะฟะพะฝััั, ะะะงะะะฃ ะณัะตัะธ ะพัะดะตะปััั ะฝะฐั ะพั ะัะตะฒััะฝะตะณะพ, ะะปััะตั ะะตะฑะต ะดะพะปะถะตะฝ ัะฝะฐัะฐะปะฐ ะฝะฐััะธัั ะฝะฐั ัะพัั ะฑั ะฝะตะผะฝะพะณะพ ะพะฑ ืึทืึฐืืึผืช ืืณ (ะะดะธะฝััะฒะต ะัะตะฒััะฝะตะณะพ)."
          },
          {
            "type": "text",
            "text": "ะะพะฝััั, ะบะฐะบ ะัะตะฒััะฝะธะน - ััะพ ะฒัั, ะธ ะฝะธััะพ ะฝะต ะธะทะผะตะฝัะตั ะะณะพ."
          },
          {
            "type": "text",
            "text": "ะกัะธั ะณะพะฒะพัะธั: \"ะกะปะพะฒะพะผ ะัะตะฒััะฝะตะณะพ ะฝะตะฑะตัะฐ ัะพะทะดะฐะฝั\" - ััะพ ะัะตะฒััะฝะธะน ัะพะทะดะฐะป ะผะธั ั \"ืึดึผืึผืึผืจ (ัะตััั)\"."
          },
          {
            "type": "text",
            "text": "ะ ัะปะตะดัััะธะต ะฝะตัะบะพะปัะบะพ ะดะฝะตะน ะะปััะตั ะะตะฑะต ะฟะพะบะฐะถะตั ะฝะฐะผ, ะบะฐะบ ะัะตะฒััะฝะธะน ะฝะต ะธะทะผะตะฝัะตััั ะฟะพัะปะต ัะพะทะดะฐะฝะธั ะผะธัะฐ."
          },
          {
            "type": "text",
            "text": "ะะฝ ะพะฑัััะฝะธั ะฟัะธััั ะพ ะดะธะฑัั ะธ ััะพ ะดะธะฑัั ะพะทะฝะฐัะฐะตั ะฒ ะฒัััะธั ะผะธัะฐั."
          },
          {
            "type": "heading",
            "text": "ะะธั ะฝะต ะฟัะธะทะฝะฐัั ะะดะธะฝััะฒะพ"
          },
          {
            "type": "text",
            "text": "ะั ัะฒะธะดะธะผ, ััะพ ะัะตะฒััะฝะธะน ัะพะทะดะฐัั ะผะธั ัะฐะบะธะผ ะพะฑัะฐะทะพะผ, ััะพ ะพะฝ ะฝะต ะฟัะธะทะฝะฐะตั ะัะดัั ะัะตะผ ัะฐะผ ะฟะพ ัะตะฑะต."
          },
          {
            "type": "text",
            "text": "ะะฝ ะฑัะดะตั ััะฒััะฒะพะฒะฐัั ัะตะฑั ะพัะดะตะปัะฝัะผ, ััะพ ัะฒะปัะตััั ะธะดะตะตะน ืขึฒืืึนืึธื ืึธืจึธื (ะธะดะพะปะพะฟะพะบะปะพะฝััะฒะฐ)."
          },
          {
            "type": "highlight",
            "text": "ะะพะณะดะฐ ะตะฒัะตะน ะฝะต ะดะตะปะฐะตั ัะพ, ััะพ ะัะตะฒััะฝะธะน ัะพัะตั, ะพะฝ ะพัะดะตะปัะตััั ะพั ะัะดัั ะัะตะผ ะธ ัะพะตะดะธะฝัะตััั ั ะะฒะพะดะฐ ะะฐัะฐ ะผะธัะฐ."
          },
          {
            "type": "text",
            "text": "ะะพะณะดะฐ ะผั ะพัะพะทะฝะฐะตะผ ััะพ, ะผั ะฝะธะบะพะณะดะฐ ะฝะต ะฟะพะทะฒะพะปะธะผ ััะพะผั ัะปััะธัััั!"
          }
        ]
      }
    },
    {
      "id": "hayom-yom",
      "title": "ะะะะ ะะะ",
      "subtitle": "5 ะจะฒะฐัะฐ - ะะพะฒะพัะธัั ัะปะพะฒะฐ ะขะพัั",
      "icon": "๐",
      "category": "hayom-yom",
      "color": "#FFEAA7",
      "points": 35,
      "content": {
        "title": "ืึดึผืึฐืึทืจ ืืณ ืฉึธืืึทืึดื ืึทืขึฒืฉืืึผ - ะฃะบัะตะฟะปััั ะผะธั ัะปะพะฒะฐะผะธ ะขะพัั",
        "paragraphs": [
          {
            "type": "text",
            "text": "ะ ัะตะณะพะดะฝััะฝะตะผ ะะนะพะผ ะะพะผ ะผั ัะทะฝะฐัะผ, ะบะฐะบ ะฒะฐะถะฝะพ ะธัะฟะพะปัะทะพะฒะฐัั ะฝะฐัั ัะธะปั ัะตัะธ, ััะพะฑั ะฒัะตะณะดะฐ ะณะพะฒะพัะธัั ัะปะพะฒะฐ ะขะพัั!"
          },
          {
            "type": "heading",
            "text": "ะะฐะฐะผะฐั \"ะะธะดะฒะฐั ะัะตะผ\""
          },
          {
            "type": "text",
            "text": "ะ ะผะฐะฐะผะฐัะต, ะบะพัะพััะน ะฝะฐัะธะฝะฐะตััั ัะปะพะฒะฐะผะธ \"ะะธะดะฒะฐั ะัะตะผ ะจะฐะผะฐะธะผ ะะฐะฐัั\", ะคัะธะตัะดะธะบะตั ะะตะฑะต ะพะฑัััะฝัะตั, ััะพ ะทะฝะฐัะธั, ััะพ ะัะตะฒััะฝะธะน ัะพะทะดะฐะป ะผะธั ั ืึดึผืึผืึผืจ (ัะตััั)."
          },
          {
            "type": "text",
            "text": "ะะฐัะตะผ ะคัะธะตัะดะธะบะตั ะะตะฑะต ะณะพะฒะพัะธั, ััะพ ะฟัะธัะธะฝะฐ, ะฟะพัะตะผั ะัะตะฒััะฝะธะน ัะพะทะดะฐะป ะผะธั ั ะดะธะฑัั - ััะพ ััะพะฑั ะตะฒัะตะน ะธัะฟะพะปัะทะพะฒะฐะป ัะฒะพะน ะดะธะฑัั ะดะปั ัะบัะตะฟะปะตะฝะธั ะผะธัะฐ, ะบะพัะพััะน ะัะตะฒััะฝะธะน ัะพะทะดะฐะป ั ะดะธะฑัั!"
          },
          {
            "type": "heading",
            "text": "ืึดืึผืึผื ืึทืงึถึผืึถืจ ืึฐืึทืฃ ืึทืงึถึผืึทืข - ะัะธัะตะฝะธะต ะดััะธ"
          },
          {
            "type": "text",
            "text": "ะะพ ะฒัะพัะพะน ะฟะพะปะพะฒะธะฝะต ัะพะณะพ ะผะฐะฐะผะฐัะฐ ะคัะธะตัะดะธะบะตั ะะตะฑะต ัะฟะพะผะธะฝะฐะตั, ััะพ ะฟัะพะธััะพะดะธั ั ะดััะพะน ะฟะพัะปะต ัะพะณะพ, ะบะฐะบ ะพะฝะฐ ะทะฐะบะฐะฝัะธะฒะฐะตั ัะฒะพั ะผะธััะธั ะฒ ััะพะผ ะผะธัะต."
          },
          {
            "type": "text",
            "text": "ะัะปะธ ัะตะปะพะฒะตะบ ััะฐัะธะป ัะฒะพั ะฒัะตะผั ะธ ะผะฝะพะณะพ ะณะพะฒะพัะธะป ะณะปัะฟะพััะตะน, ะดััะต ะฝัะถะฝะพ ะพัะพะฑะพะต ะพัะธัะตะฝะธะต, ะฝะฐะทัะฒะฐะตะผะพะต ะฅะธะฑัั ะฐะะตะฒะตั (ะฟะพะฑะพะธ ะฒ ะผะพะณะธะปะต) ะธ ะะฐั ะฐะะตะปะฐ (ะบะฐัะฐะฟัะปััะฐ)."
          },
          {
            "type": "heading",
            "text": "ะกะพะฒะตั ะคัะธะตัะดะธะบะตั ะะตะฑะต"
          },
          {
            "type": "text",
            "text": "ะกะตะณะพะดะฝััะฝะธะน ะะนะพะผ ะะพะผ - ััะพ ะฟะพัะปะตะดะฝะธะต ะฝะตัะบะพะปัะบะพ ัััะพะบ ัะพะณะพ ะผะฐะฐะผะฐัะฐ:"
          },
          {
            "type": "highlight",
            "text": "ะงะตะปะพะฒะตะบ ะดะพะปะถะตะฝ ะณะพะฒะพัะธัั ะผะฝะพะณะพ ัะปะพะฒ ะขะพัั (ะฝะฐะฟัะธะผะตั, ะณะพะฒะพัะธัั ะขะตะธะปะธะผ ะธะปะธ ะฟะพะฒัะพัััั ะะธัะฝะฐะนะพั) ะบะพะณะดะฐ ะธ ะณะดะต ัะพะปัะบะพ ะผะพะถะตั!"
          },
          {
            "type": "text",
            "text": "ะะพัะตะผั ััะพ ัะฐะบ ะฒะฐะถะฝะพ?"
          },
          {
            "type": "text",
            "text": "1๏ธโฃ ะญัะพ ัะบัะตะฟะธั ะผะธั (ะฟะพัะพะผั ััะพ ะดะปั ััะพะณะพ ะัะตะฒััะฝะธะน ะตะณะพ ัะพะทะดะฐะป)"
          },
          {
            "type": "text",
            "text": "2๏ธโฃ ะญัะพ ัะฟะฐััั ะตะณะพ ะพั ะฝะตะพะฑัะพะดะธะผะพััะธ ะฅะธะฑัั ะฐะะตะฒะตั ะธ ะะฐั ะฐะะตะปะฐ"
          },
          {
            "type": "text",
            "text": "3๏ธโฃ ะะณะพ ะดััะฐ ัะผะพะถะตั ะพัะตะฝะธัั ืึฑืึนืงืึผืช (ะะพะถะตััะฒะตะฝะฝะพััั)"
          },
          {
            "type": "heading",
            "text": "ะัะฐะบัะธัะตัะบะพะต ะฟัะธะผะตะฝะตะฝะธะต"
          },
          {
            "type": "example",
            "title": "ะะฐะบ ัะบัะตะฟะปััั ะผะธั ัะตััั",
            "text": "โข ะะพะฒะพัะธัั ะขะตะธะปะธะผ ะฒ ะปัะฑะพะต ะฒัะตะผั\nโข ะะพะฒัะพัััั ะะธัะฝะฐะนะพั ะฟะพ ะดะพัะพะณะต\nโข ะฃัะธัั ะขะพัั ะบะพะณะดะฐ ะตััั ัะฒะพะฑะพะดะฝะฐั ะผะธะฝััะฐ\nโข ะัะฟะพะปัะทะพะฒะฐัั ะบะฐะถะดัั ะฒะพะทะผะพะถะฝะพััั ะดะปั ัะฒััะพะน ัะตัะธ"
          },
          {
            "type": "highlight",
            "text": "ะัะตะฒััะฝะธะน ัะพะทะดะฐะป ะผะธั ะกะะะะะ - ะธ ะผั ัะบัะตะฟะปัะตะผ ััะพั ะผะธั ะฝะฐัะธะผะธ ะกะะะะะะ ะขะพัั!"
          },
          {
            "type": "text",
            "text": "ะญัะพ ะพัะพะฑะตะฝะฝะพ ะฒะฐะถะฝะพ ัะตะนัะฐั, ะบะพะณะดะฐ ะผั ะฟัะธะฑะปะธะถะฐะตะผัั ะบ ืืึผื ืึดืึผืึผืึธื (ะัะด ะจะฒะฐัั) - ะดะฝั, ะบะพะณะดะฐ ะคัะธะตัะดะธะบะตั ะะตะฑะต ะฒะตัะฝัะปัั ะบ ะัะตะฒััะฝะตะผั ะธ ะะตะฑะต ะฟัะธะฝัะป ะฝะฐ ัะตะฑั ืึฐืฉึดืืืืึผืช (ััะบะพะฒะพะดััะฒะพ)."
          }
        ]
      }
    },
    {
      "id": "rambam",
      "title": "ะะะะะะ",
      "subtitle": "ะฃัะพะบ 329 - ะกะปััะฐัััั ะกะฐะฝะตะดัะธะฝ",
      "icon": "โ๏ธ",
      "category": "rambam",
      "color": "#96CEB4",
      "points": 45,
      "content": {
        "title": "ืึทืึฐืจึดืื - ะ ัะตั, ะบัะพ ะฝะต ัะปััะฐะตััั",
        "paragraphs": [
          {
            "type": "text",
            "text": "ะกะตะณะพะดะฝั ะผั ะฝะฐัะธะฝะฐะตะผ ะฝะพะฒัะน ัะฐะทะดะตะป ะฒ ะะฐะผะฑะฐะผะต ะพ ะปัะดัั, ะบะพัะพััะต ะฝะต ัะปััะฐัั ัะพ, ัะตะผั ััะธั ะขะพัะฐ."
          },
          {
            "type": "heading",
            "text": "ะงะตัััะต ะทะฐะฟะพะฒะตะดะธ ะฝะฐ ัะตะณะพะดะฝั"
          },
          {
            "type": "text",
            "text": "ะ ัะตะณะพะดะฝััะฝะตะผ ะกะตัะตั ะฐะะธัะฒะพั ะผั ััะธะผ ัะตัััะต ะผะธัะฒะพั:"
          },
          {
            "type": "heading",
            "text": "1๏ธโฃ ะะฐะฟะพะฒะตะดั #174 (ืขึฒืฉึตืื) - ะกะปััะฐัััั ะกะฐะฝะตะดัะธะฝ"
          },
          {
            "type": "text",
            "text": "ะั ะดะพะปะถะฝั ัะปััะฐัั ะฒัั, ััะพ ะฟะพััะฐะฝะพะฒะปัะตั ืกึทืึฐืึถืึฐืจึดืื."
          },
          {
            "type": "text",
            "text": "ะั ััะธะผ ััั ะผะธัะฒั ะธะท ััะธัะฐ ะฒ ะฝะตะดะตะปัะฝะพะน ะณะปะฐะฒะต ะจะพััะธะผ:"
          },
          {
            "type": "text",
            "text": "\"ืขึทื ืคึดึผื ืึทืชึผืึนืจึธื ืึฒืฉึถืืจ ืืึนืจืึผืึธ\" - \"ะะพ ะขะพัะต, ะบะพัะพัะพะน ะฝะฐััะฐั ัะตะฑั\""
          },
          {
            "type": "text",
            "text": "ะะตัะฐะปะธ ะพะฑัััะฝััััั ะฒ ะบะพะฝัะต ััะฐะบัะฐัะฐ ะกะฐะฝะตะดัะธะฝ."
          },
          {
            "type": "heading",
            "text": "2๏ธโฃ ะะฐะฟะพะฒะตะดั #312 (ืึนื ืชึทืขึฒืฉึถืื) - ะะต ะพัะบะปะพะฝััััั"
          },
          {
            "type": "text",
            "text": "ะะฐะผ ะฝะต ัะฐะทัะตัะตะฝะพ ะะ ัะปััะฐัั ัะพ, ัะตะผั ััะฐั ะฝะฐั ืึฒืึธืึดืื (ะัะดัะตัั)."
          },
          {
            "type": "text",
            "text": "ะั ััะธะผ ััั ะผะธัะฒั ะธะท ััะธัะฐ ะฒ ะฝะตะดะตะปัะฝะพะน ะณะปะฐะฒะต ะจะพััะธะผ:"
          },
          {
            "type": "text",
            "text": "\"ืึนื ืชึธืกืึผืจ ืึดื ืึทืึธึผืึธืจ ืึฒืฉึถืืจ ืึทืึดึผืืืึผ ืึฐืึธ\" - \"ะะต ะพัะบะปะพะฝัะนัั ะพั ัะปะพะฒะฐ, ะบะพัะพัะพะต ัะบะฐะถัั ัะตะฑะต\""
          },
          {
            "type": "heading",
            "text": "3๏ธโฃ ะะฐะฟะพะฒะตะดั #313 (ืึนื ืชึทืขึฒืฉึถืื) - ะะต ะดะพะฑะฐะฒะปััั"
          },
          {
            "type": "text",
            "text": "ะั ะฝะต ะผะพะถะตะผ ะดะพะฑะฐะฒะปััั ะฝะธัะตะณะพ ะบ ะขะพัะต."
          },
          {
            "type": "text",
            "text": "ะั ััะธะผ ััั ะผะธัะฒั ะธะท ััะธัะฐ ะฒ ะฝะตะดะตะปัะฝะพะน ะณะปะฐะฒะต ะะตั:"
          },
          {
            "type": "text",
            "text": "\"ืึนื ืชึนืกึตืฃ ืขึธืึธืื\" - \"ะะต ะฟัะธะฑะฐะฒะปัะน ะบ ะฝะตะผั\""
          },
          {
            "type": "heading",
            "text": "4๏ธโฃ ะะฐะฟะพะฒะตะดั #314 (ืึนื ืชึทืขึฒืฉึถืื) - ะะต ัะฑะฐะฒะปััั"
          },
          {
            "type": "text",
            "text": "ะั ะฝะต ะผะพะถะตะผ ัะฑะธัะฐัั ะฝะธัะตะณะพ ะธะท ะขะพัั."
          },
          {
            "type": "text",
            "text": "ะั ััะธะผ ััั ะผะธัะฒั ะธะท ััะธัะฐ ะฒ ะฝะตะดะตะปัะฝะพะน ะณะปะฐะฒะต ะะตั:"
          },
          {
            "type": "text",
            "text": "\"ืึฐืึนื ืชึดืึฐืจึทืข ืึดืึถึผืึผืึผ\" - \"ะ ะฝะต ัะฑะฐะฒะปัะน ะพั ะฝะตะณะพ\""
          },
          {
            "type": "heading",
            "text": "ืึดืึฐืืึนืช ืึทืึฐืจึดืื - ะะฐะบะพะฝั ะะตะฟะพะบะพัะฝัั"
          },
          {
            "type": "highlight",
            "text": "ะ ัะตะณะพะดะฝััะฝะตะผ ะะฐะผะฑะฐะผะต ะผั ัะทะฝะฐัะผ, ััะพ ะดะฐะถะต ัะพั, ะบัะพ ะพัะตะฝั ัะผัะฝ ะธ ะทะฝะฐะตั ัะฐะบ ะผะฝะพะณะพ ะขะพัั, ะฒัั ัะฐะฒะฝะพ ะดะพะปะถะตะฝ ัะปะตะดะพะฒะฐัั ัะพะผั, ััะพ ะณะพะฒะพัะธั ะะตะนั ะะธะฝ."
          },
          {
            "type": "text",
            "text": "ะะพัะตะผั? ะะพัะพะผั ััะพ ะัะตะฒััะฝะธะน ัะพัะตั, ััะพะฑั ัะพะปัะบะพ ะะะะ ะผะตััะพ ะฑัะปะพ ะณะปะฐะฒะฝัะผ ะธ ะฒะตะปะพ ะตะฒัะตะตะฒ."
          },
          {
            "type": "heading",
            "text": "ะะปะฐะฒะฐ 1: ืชึผืึนืจึธื ืฉึถืืึฐึผืขึทื ืคึถึผื"
          },
          {
            "type": "text",
            "text": "ะั ะฟะพะปะฐะณะฐะตะผัั ะฝะฐ ะกะฐะฝะตะดัะธะฝ, ััะพะฑั ะฟะพะฝะธะผะฐัั ะขะพัั ะจะตะฑะฐะฐะป ะะต (ะฃััะฝัั ะขะพัั)."
          },
          {
            "type": "highlight",
            "text": "ะั ะดะพะปะถะฝั ัะปััะฐัั ัะพ, ััะพ ะพะฝะธ ะฝะฐะผ ะณะพะฒะพััั, ะฟะพัะพะผั ััะพ ััะพ ัะฐะบ ะถะต ะฒะฐะถะฝะพ, ะบะฐะบ ัะพะฑะปัะดะตะฝะธะต ะพััะฐะปัะฝะพะน ะขะพัั!"
          },
          {
            "type": "heading",
            "text": "ะะปะฐะฒะฐ 2: ะัะฐะฒะธะปะฐ ะดะปั ะทะฐัะธัั ะขะพัั"
          },
          {
            "type": "text",
            "text": "ะะตะนั ะะธะฝ ะผะพะถะตั ัะพะทะดะฐะฒะฐัั ะฟัะฐะฒะธะปะฐ, ััะพะฑั ะตะฒัะตะธ ะปัััะต ัะพะฑะปัะดะฐะปะธ ะขะพัั."
          },
          {
            "type": "text",
            "text": "ะะพ ะะตะนั ะะธะฝ ะดะพะปะถะตะฝ ะดะตะปะฐัั ัะฐะบะธะต ะฟัะฐะฒะธะปะฐ ัะพะปัะบะพ ะตัะปะธ ะพะฝะธ ัะฒะตัะตะฝั, ััะพ ะฑะพะปััะธะฝััะฒะพ ะตะฒัะตะตะฒ ะผะพะณัั ะธั ัะพะฑะปัะดะฐัั."
          },
          {
            "type": "heading",
            "text": "ะะปะฐะฒะฐ 3: ะขะต, ะบัะพ ะฝะต ัะปะตะดัะตั"
          },
          {
            "type": "text",
            "text": "ะญัะฐ ะณะปะฐะฒะฐ ะณะพะฒะพัะธั ะพ ะปัะดัั, ะบะพัะพััะต ะฝะต ัะปะตะดััั ัะพะผั, ััะพ ะณะพะฒะพัะธั ะกะฐะฝะตะดัะธะฝ:"
          },
          {
            "type": "text",
            "text": "**ะััะธัะฐะฝะธะต ะฃััะฝะพะน ะขะพัั:**\nะัะปะธ ัะตะปะพะฒะตะบ ัะตัะฐะตั, ััะพ ะฝะต ะฒะตัะธั ะฒ ะขะพัั ะจะตะฑะฐะฐะป ะะต, ะพะฝ ะฝะต ะฟัะพััะพ ะฒะพัััะฐัั ะฟัะพัะธะฒ ะัะดัะตัะพะฒ - ะพะฝ ะธะดัั ะฟัะพัะธะฒ ะฒัะตะน ะขะพัั!"
          },
          {
            "type": "heading",
            "text": "ะ ืฉึฐืืึดืืืึผืช (ะผะธััะธะธ)"
          },
          {
            "type": "text",
            "text": "ะ ัะตะฟะตัั ะะฐะผะฑะฐะผ ะณะพะฒะพัะธั ะพ ัะปะธััั!"
          },
          {
            "type": "highlight",
            "text": "ะัะปะธ ัะตะปะพะฒะตะบ ะฝะต ะฒะตัะธั ะฒ ะขะพัั ะจะตะฑะฐะฐะป ะะต, ะฟะพัะพะผั ััะพ ััะพะผั ะตะณะพ ะฝะฐััะธะปะธ ัะพะดะธัะตะปะธ, ะตะณะพ ะฝะต ัะปะตะดัะตั ะฝะฐะบะฐะทัะฒะฐัั."
          },
          {
            "type": "text",
            "text": "ะญัะพ ะฝะต ะตะณะพ ะฒะธะฝะฐ, ััะพ ะพะฝ ะฝะต ะทะฝะฐะตั ะปัััะต!"
          },
          {
            "type": "example",
            "title": "ะะฐะบ ะผะปะฐะดะตะฝะตั",
            "text": "ะะฝ ะบะฐะบ ะผะฐะปะตะฝัะบะธะน ัะตะฑัะฝะพะบ, ะบะพัะพัะพะณะพ ะทะฐัะฒะฐัะธะปะธ ะธ ะฒััะฐััะธะปะธ ะฒ ะฝะตะตะฒัะตะนัะบะพะผ ะดะพะผะต, ะธ ะฝะต ััะธะปะธ ะขะพัะต. ะะผะตััะพ ะฝะฐะบะฐะทะฐะฝะธั ะผั ะดะพะปะถะฝั ะฟะพะฟััะฐัััั ััะธัั ะตะณะพ ะขะพัะต ะปัะฑััะธะผ ะพะฑัะฐะทะพะผ, ััะพะฑั ะพะฝ ะฒัััะธะป ะฟัะฐะฒะธะปัะฝัะน ะฟััั!"
          },
          {
            "type": "heading",
            "text": "ืึธืงึตื ืึทืึฐืจึตื - ะัะฝััััะธะน ะผัะดัะตั"
          },
          {
            "type": "text",
            "text": "ืชึทึผืึฐืึดืื ืึธืึธื (ะฃััะฝัะน ะขะพัั), ะบะพัะพััะน ะฟะพััะฐะฝะพะฒะปัะตั ะธะฝะฐัะต, ัะตะผ ะกะฐะฝะตะดัะธะฝ, ะฒะธะฝะพะฒะตะฝ ะฒ ัะผะตััะฝะพะน ะบะฐะทะฝะธ."
          },
          {
            "type": "text",
            "text": "ะะพัะตะผั ัะฐะบะพะต ัััะพะณะพะต ะฝะฐะบะฐะทะฐะฝะธะต?"
          },
          {
            "type": "highlight",
            "text": "ะะพัะพะผั ััะพ ะพะฝ ะทะฐััะฐะฒะปัะตั ะตะฒัะตะตะฒ ะฝะต ะธะผะตัั ืึทืึฐืืึผืช (ะตะดะธะฝััะฒะฐ) - ะพะฝ ะทะฐััะฐะฒะปัะตั ะธั ะดะตะนััะฒะพะฒะฐัั ะฟะพ-ะดััะณะพะผั, ัะตะผ ะฒัะต ะพััะฐะปัะฝัะต!"
          },
          {
            "type": "text",
            "text": "ะัะตะฒััะฝะธะน ัะพัะตั, ััะพะฑั ะฒัะต ะตะฒัะตะธ ะฑัะปะธ ะตะดะธะฝั ะธ ัะปะตะดะพะฒะฐะปะธ ะพะดะฝะพะผั ััะบะพะฒะพะดััะฒั."
          }
        ]
      }
    },
    {
      "id": "geula",
      "title": "ะะะฃะะ ะ ะะะจะะะฅ",
      "subtitle": "ะ ะทะฐัะปัะณั ะฟัะฐะฒะตะดะฝัั ะถะตะฝัะธะฝ",
      "icon": "๐",
      "category": "geula",
      "color": "#DFE6E9",
      "points": 30,
      "content": {
        "title": "ืึดึผืึฐืืึผืช ืึธืฉึดืืื ืฆึดืึฐืงึธืึดืึผืึนืช - ะะตะฝัะธะฝั ะฟัะธะฝะพััั ะะตัะปั",
        "paragraphs": [
          {
            "type": "heading",
            "text": "ะะฑะตัะฐะฝะธะต ะัะพัะพะบะฐ"
          },
          {
            "type": "text",
            "text": "ืึธืึดืื (ะัะพัะพะบ) ะณะพะฒะพัะธั:"
          },
          {
            "type": "highlight",
            "text": "\"ืึดึผืืึตื ืฆึตืืชึฐืึธ ืึตืึถืจึถืฅ ืึดืฆึฐืจึทืึดื ืึทืจึฐืึถืึผืึผ ืึดืคึฐืึธืืึนืช\" - \"ะะฐะบ ะฒ ะดะฝะธ ัะฒะพะตะณะพ ะฒััะพะดะฐ ะธะท ะทะตะผะปะธ ะะณะธะฟะตััะบะพะน, ะฟะพะบะฐะถั ะตะผั ััะดะตัะฐ\"."
          },
          {
            "type": "text",
            "text": "ะะพ ะฒัะตะผั ืึฐึผืืึผืึธึผื ะัะตะฒััะฝะธะน ะฟะพะบะฐะถะตั ะฝะฐะผ ััะดะตัะฐ, ะบะฐะบ ะะฝ ัะดะตะปะฐะป, ะบะพะณะดะฐ ะผั ะฒััะปะธ ะธะท ะะณะธะฟัะฐ."
          },
          {
            "type": "text",
            "text": "ะัััะดะฐ ะผั ัะทะฝะฐัะผ, ััะพ ืึฐืฆึดืืึทืช ืึดืฆึฐืจึทืึดื (ะััะพะด ะธะท ะะณะธะฟัะฐ) - ััะพ ะฟัะธะผะตั ะดะปั ืึฐืืึผืึธึผื (ะะทะฑะฐะฒะปะตะฝะธั) ะะพัะธะฐัะฐ!"
          },
          {
            "type": "heading",
            "text": "ะะดะธะฝะฐะบะพะฒะฐั ะฟัะธัะธะฝะฐ ะะตัะปั"
          },
          {
            "type": "text",
            "text": "ะะพั ะพะดะธะฝ ะธะท ัะฟะพัะพะฑะพะฒ, ะบะพัะพััะผ ะพะฝะธ ะพะดะธะฝะฐะบะพะฒั:"
          },
          {
            "type": "text",
            "text": "ะะพะฒะพัะธััั ะพ ะััะพะดะต ะธะท ะะณะธะฟัะฐ, ััะพ ะพะฝ ะฟัะธััะป ะฒ ะทะฐัะปัะณั ะถะตะฝัะธะฝ:"
          },
          {
            "type": "highlight",
            "text": "\"ืึดึผืึฐืืึผืช ืึธืฉึดืืื ืฆึดืึฐืงึธืึดืึผืึนืช ืึดืึฐืึฒืืึผ ืึฒืืึนืชึตืืืึผ\" - \"ะ ะทะฐัะปัะณั ะฟัะฐะฒะตะดะฝัั ะถะตะฝัะธะฝ ะฑัะปะธ ะธะทะฑะฐะฒะปะตะฝั ะฝะฐัะธ ะพััั\"."
          },
          {
            "type": "text",
            "text": "ะะพัะธะฐั ัะฐะบะถะต ะฟัะธะดัั ะฒ ะทะฐัะปัะณั ืึธืฉึดืืื ืฆึดืึฐืงึธืึดืึผืึนืช (ะฟัะฐะฒะตะดะฝัั ะถะตะฝัะธะฝ) ะฝะฐัะตะณะพ ะฒัะตะผะตะฝะธ!"
          },
          {
            "type": "heading",
            "text": "ะัะพะฑะฐั ะทะฐะฑะพัะฐ ะะตะฑะต"
          },
          {
            "type": "text",
            "text": "ะะผะตะฝะฝะพ ะฟะพััะพะผั ะคัะธะตัะดะธะบะตั ะะตะฑะต ะธ ะะตะฑะต ะพัะตะฝั ััะฐัะตะปัะฝะพ ัะปะตะดะธะปะธ ะทะฐ ัะตะผ, ััะพะฑั ะดะตะฒะพัะบะธ ะธ ะถะตะฝัะธะฝั ะธะผะตะปะธ ะพัะตะฝั ัะพัะพัะตะต ืึดืืึผืึผืึฐ (ะฒะพัะฟะธัะฐะฝะธะต)."
          },
          {
            "type": "example",
            "title": "ะะพะปััะต, ัะตะผ ะดััะณะธะต ะฟะพะบะพะปะตะฝะธั",
            "text": "ะัะพะฑะตะฝะฝะพ ะฟะพ ััะฐะฒะฝะตะฝะธั ั ะะตะฑะต ะดััะณะธั ะฟะพะบะพะปะตะฝะธะน, ะพะฝะธ ะดะฐะฒะฐะปะธ ัะฐะบ ะผะฝะพะณะพ ัะฒะพะตะณะพ ะฒัะตะผะตะฝะธ ะธ ัะธะป ะดะปั ััะพะณะพ!"
          },
          {
            "type": "text",
            "text": "ะัะปะธ ัะฟะตัะธะฐะปัะฝัะต ะฟะธััะผะฐ, ะฑะตัะตะดั ะธ ัะบะฐะทะฐะฝะธั ัะพะปัะบะพ ะดะปั ะถะตะฝัะธะฝ."
          },
          {
            "type": "heading",
            "text": "ะฆะตะปั ััะพะน ะทะฐะฑะพัั"
          },
          {
            "type": "text",
            "text": "ะัั ััะพ ะฑัะปะพ ะดะปั ัะพะณะพ, ััะพะฑั ัะฑะตะดะธัััั, ััะพ ะถะตะฝัะธะฝั ะฝะฐัะตะณะพ ะฒัะตะผะตะฝะธ ะฑัะดัั ืึธืฉึดืืื ืฆึดืึฐืงึธืึดืึผืึนืช."
          },
          {
            "type": "highlight",
            "text": "ะขะต, ะบัะพ ะฟัะธะฝะตััั ะะพัะธะฐัะฐ ะฒ ะธั ะทะฐัะปัะณั!"
          },
          {
            "type": "heading",
            "text": "ะัะธะผะตัั ะพัะพะฑะพะณะพ ะฒะฝะธะผะฐะฝะธั"
          },
          {
            "type": "text",
            "text": "๐ง **ะัะพะฑัะต ะฟะธััะผะฐ** - ะะตะฑะต ะฟะธัะฐะป ะผะฝะพะณะพ ะฟะธัะตะผ ัะฟะตัะธะฐะปัะฝะพ ะถะตะฝัะธะฝะฐะผ"
          },
          {
            "type": "text",
            "text": "๐ฃ๏ธ **ะัะพะฑัะต ะฑะตัะตะดั** - ะัะปะธ ัะฐัะฑัะตะฝะณะตะฝั ะธ ัะธัะพั ัะพะปัะบะพ ะดะปั ะถะตะฝัะธะฝ"
          },
          {
            "type": "text",
            "text": "๐ **ะัะพะฑัะต ัะบะฐะทะฐะฝะธั** - ะะตะฑะต ะดะฐะฒะฐะป ัะฟะตัะธะฐะปัะฝัะต ืืึนืจึธืืึนืช (ััะบะพะฒะพะดััะฒะฐ) ะดะปั ะถะตะฝัะธะฝ"
          },
          {
            "type": "text",
            "text": "๐ง **ะะฑัะฐะทะพะฒะฐะฝะธะต ะดะตะฒะพัะตะบ** - ะัะพะฑะพะต ะฒะฝะธะผะฐะฝะธะต ัะธะฝัั ะดะตะฒะพัะตะบ ั ัะฐะฝะฝะตะณะพ ะฒะพะทัะฐััะฐ"
          },
          {
            "type": "heading",
            "text": "ะกะฒัะทั ั ะัะด ะจะฒะฐั"
          },
          {
            "type": "text",
            "text": "ะงะตัะตะท ะฝะตัะบะพะปัะบะพ ะดะฝะตะน ะฑัะดะตั ืืึผื ืึดืึผืึผืึธื (ะัะด ะจะฒะฐั) - ะดะตะฝั, ะบะพะณะดะฐ ะะตะฑะต ะฟัะธะฝัะป ะฝะฐ ัะตะฑั ืึฐืฉึดืืืืึผืช."
          },
          {
            "type": "text",
            "text": "ะะดะฝะฐ ะธะท ะณะปะฐะฒะฝัั ะฒะตัะตะน, ะบะพัะพััั ะะตะฑะต ะดะตะปะฐะป ะฒัั ัะฒะพั ััะบะพะฒะพะดััะฒะพ - ััะพ ะทะฐะฑะพัะฐ ะพ ะถะตะฝัะธะฝะฐั ะธ ะดะตะฒะพัะบะฐั."
          },
          {
            "type": "highlight",
            "text": "ะญัะพ ะฟะพะบะฐะทัะฒะฐะตั, ะบะฐะบ ะฒะฐะถะฝะฐ ัะพะปั ะถะตะฝัะธะฝ ะฒ ะฟัะธะฒะตะดะตะฝะธะธ ะพะบะพะฝัะฐัะตะปัะฝะพะน ะะตัะปั!"
          },
          {
            "type": "text",
            "text": "ะะพะณะดะฐ ะถะตะฝัะธะฝั ะธ ะดะตะฒะพัะบะธ ะฒัะฟะพะปะฝััั ัะฒะพั ะพัะพะฑัั ะผะธััะธั, ะผั ััะบะพััะตะผ ะฟัะธัะพะด ะะพัะธะฐัะฐ."
          },
          {
            "type": "text",
            "text": "ะะผะตะฝะฝะพ ะฒ ะธั ืึฐืืึผืช (ะทะฐัะปัะณั) ะฟัะธะดัั ืึฐืืึผืึธึผื - ัะฐะบ ะถะต, ะบะฐะบ ััะพ ะฑัะปะพ ะฒ ะะณะธะฟัะต!"
          }
        ]
      }
    }
  ]
}
